app_templates
