Metadata-Version: 2.1
Name: create-eel-app
Version: 0.1.2
Summary: To bootstrap a basic Eel app.
Home-page: https://github.com/gr3atwh173/create_eel_app
Author: gr3atwh173
License: UNKNOWN
Keywords: eel,create_eel_app
Platform: UNKNOWN
Requires-Python: >=3.5
